django_extended_choices-1.3.3.dist-info/DESCRIPTION.rst
django_extended_choices-1.3.3.dist-info/LICENSE.txt
django_extended_choices-1.3.3.dist-info/METADATA
django_extended_choices-1.3.3.dist-info/RECORD
django_extended_choices-1.3.3.dist-info/WHEEL
django_extended_choices-1.3.3.dist-info/metadata.json
django_extended_choices-1.3.3.dist-info/top_level.txt
django_extended_choices-1.3.3.dist-info/zip-safe
extended_choices/__init__.py
extended_choices/__main__.py
extended_choices/choices.py
extended_choices/fields.py
extended_choices/helpers.py
extended_choices/tests.py
